{"date":"2012-05-19","time":"16:00","venue":"Hindu Temple of Atlanta","artists":[{"name":"Sangeetha Kalanidhi R.K. Srikantan","instrument":"Vocal"},{"name":"R.S.Ramakanth","instrument":"Vocal Support"},{"name":"Mantraratnam Prasad","instrument":"Violin"},{"name":"Ram Sriram","instrument":"Mridangam"}],"songs":[{"name":"Sami Ninne Kori","ragam":"Sri","talam":"Adi","composer":"Karur Devudu Iyer"},{"name":"Sri Mahaganapathi","ragam":"Gowlai","talam":"M. Chapu","composer":"Dikshatar"},{"name":"Jaya Mahishasura Mardini","ragam":"Hamsadwani","talam":"Roopakam","composer":"Muthiah Bhagavathar"},{"name":"Gopa Nandana","ragam":"Bhoosavali","talam":"Adi","composer":"Swathi Thirunal"},{"name":"Mama Hrudaye","ragam":"Reethigowlai","talam":"Adi","composer":"Mysore Vasudevachariar"},{"name":"Vande Sadaa Padmanaabam","ragam":"Navarasa Kaanada","talam":"Adi","composer":"Swathi Thirunal"},{"name":"Raman  nee Samana","ragam":"Kharaharapriya","talam":"Roopakam","composer":"Thiagarajar"},{"name":"Manda gamane","ragam":"Kamas","talam":"Adi","composer":"Purandaradasa"},{"name":"Nara Narada","ragam":"Nadanamakriya","talam":"Adi","composer":"Purandaradasa"},{"name":"Japata Matida","ragam":"Hindolam"},{"name":"Kayo Karunanide","ragam":"Yamankalyani","talam":"Adi","composer":"Purandaradasa"}],"photos":[{"src":"RKSrikantan_2012.JPG","title":"RKSrikantan_2012"}]}