{"date":"2006-10-08","time":"16:00","venue":"Hindu Temple of Atlanta","artists":[{"name":"Sangeetha Sivakumar","instrument":"Vocal"},{"name":"Shreeramkumar","instrument":"Violin"},{"name":"Balaji","instrument":"Mridangam"}],"songs":[{"name":"Sarasuda","ragam":"Saveri","talam":"Kothavaasaln  Venkataraamaiyyar","composer":"Adi"},{"name":"Swaminatha Paripalayasumam","ragam":"Nattai","talam":"Adi","composer":"M.Dikshatar"},{"name":"Makelara Vicharamu","ragam":"Ravichandrika","talam":"Deshadi","composer":"Thiagarajar"},{"name":"Devi Brova Samayamithe","ragam":"Chinthamani","talam":"Adi","composer":"Shyama Sastri"},{"name":"Marivere Dikevaru","ragam":"Lathangi","talam":"Adi","composer":"Patnam Subramania Iyer"},{"name":"Enneramum undan sannidhi","ragam":"Devagandhari","talam":"Adi","composer":"Gopalakrishna Bharathi"},{"name":"Vararagalaya","ragam":"Chenchukambhoji","talam":"Adi","composer":"Thiagarajar"},{"name":"Bala Gopala","ragam":"Bhairavi","talam":"Adi","composer":"M.Dikshatar"},{"name":"Kamala Charane","ragam":"Amritha Behag","talam":"Adi","composer":"G.N. Balasubramaniam"},{"name":"RTPn  (Pallavi-Karimora vinarasa)","ragam":"Saveri followed by ragamalika","talam":"Chastusra Jamppai"},{"name":"Enna thanvam seidhane","ragam":"Kaapi","talam":"Adi","composer":"Papanasam Sivan"},{"name":"Karpuram narumo","ragam":"Kamas","talam":"Adi","composer":"Nachiar"},{"name":"Pibhara rama rasam","ragam":"Yaman kalyani","talam":"Adi","composer":"Sadasiva Brahmendrar"},{"name":"Iye metha kadinam","ragam":"Ragamalika","composer":"Gopalakrishna Bharathiar"},{"name":"Narayana nine","ragam":"Suddha Dhanyasi","talam":"Khanda Chapu","composer":"P.Dasar"},{"name":"Bare Pandu Ranga","ragam":"Abhang","composer":"Tukaram"},{"name":"Mangalam"}]}