{"date":"2015-05-30","time":"16:00","venue":"Hindu Temple of Atlanta","artists":[{"name":"Madurai T.N.Seshagopalan","instrument":"Vocal"},{"name":"Jayshankar Balan","instrument":"Violin"},{"name":"Ram S. Sriram","instrument":"Mridangam"}],"photos":[{"src":"IMG_0445.JPG","title":"Dr. Ram Sriram, Madurai T.N.Seshagopalan and Jayshankar Balan"},{"src":"IMG_0436.JPG","title":"Madurai T.N.Seshagopalan"},{"src":"IMG_0438.JPG","title":"Jayshankar Balan"},{"src":"IMG_0460.JPG","title":"Dr. Ram Sriram"},{"src":"IMG_0440.JPG","title":"Madurai T.N.Seshagopalan"},{"src":"IMG_0458.JPG","title":"Dr. Ram Sriram, Madurai T.N.Seshagopalan and Jayshankar Balan"},{"src":"IMG_0439.JPG","title":"Jayshankar Balan"},{"src":"IMG_0450.JPG","title":"Madurai T.N.Seshagopalan"},{"src":"IMG_0454.JPG","title":"Dr. Ram Sriram"},{"src":"IMG_0441.JPG","title":"Madurai T.N.Seshagopalan"},{"src":"IMG_0461.JPG","title":"Dr. Ram Sriram"},{"src":"IMG_0448.JPG","title":"Madurai T.N.Seshagopalan"},{"src":"IMG_0471.JPG","title":"Dr. Ram Sriram"}],"songs":[{"name":"Vanajakshi (Varnam)","ragam":"Kalyani","talam":"Ata","composer":"Pallavi Gopala Iyer"},{"name":"Orajupu choo","ragam":"Kannada Gowla","talam":"Adi","composer":"Thyagaraja"},{"name":"Ninnu Vinaga","ragam":"Purvikalyani","talam":"Desadi-Misra Nadai","composer":"Syama Sastri"},{"name":"Mokshamu Galada","ragam":"Saramathi","talam":"Adi","composer":"Thyagaraja"},{"name":"Ela teliya","ragam":"Darbar","talam":"Misra Chapu","composer":"Thyagaraja"},{"name":"Paradesi Petra Pillai","ragam":"Bilahari","talam":"Adi","composer":"Muthaiah Bhagavathar"},{"name":"Ka Vaa Vaa","ragam":"Varali","talam":"Adi","composer":"Papanasam Sivan"},{"name":"Enta Veduko","ragam":"Saraswathi Manohari","talam":"Desadi","composer":"Thyagaraja"},{"name":"Saravana Bhava Samayamidi","ragam":"Pasupathipriya","talam":"Adi","composer":"Muthaiah Bhagavathar"},{"name":"Arda Nareeswaram","ragam":"Kumudakriya","talam":"Rupakam","composer":"Muthuswami Dikshithar"},{"name":"Abhogi Ragathil Madhyama","ragam":"RTP- Abhogi followed by ragamalika","talam":"Triputa"},{"name":"Virutham","ragam":"Ragamalika"},{"name":"Thillana","talam":"Adi","composer":"Muthaiah Bhagavathar"},{"name":"Yeru Mayil Yeru (Thirupugazh)"},{"name":"Mangalam"}]}